pipenv_d/__init__.py
pipenv_d/__main__.py
pipenv_d/_version.py
pipenv_d/cli.py
pipenv_d/utils.py
pipenv_d-0.0.4.dist-info/METADATA
pipenv_d-0.0.4.dist-info/WHEEL
pipenv_d-0.0.4.dist-info/entry_points.txt
pipenv_d-0.0.4.dist-info/top_level.txt
pipenv_d-0.0.4.dist-info/RECORD
