Metadata-Version: 2.1
Name: pipenv-d
Version: 0.0.4
Summary: dirty hack of pipenv
Home-page: https://github.com/dboyliao/pipenv-d
Author: dboyliao
Requires-Dist: pipenv
